README.md
setup.py
topsis/_init_.py
topsis/topsis.py
topsis_by_ravsehaj.egg-info/PKG-INFO
topsis_by_ravsehaj.egg-info/SOURCES.txt
topsis_by_ravsehaj.egg-info/dependency_links.txt
topsis_by_ravsehaj.egg-info/requires.txt
topsis_by_ravsehaj.egg-info/top_level.txt