Metadata-Version: 2.1
Name: topsis-by-ravsehaj
Version: 1.0.2
Summary: A package for Topsis technique
Home-page: https://github.com/Ravsehajsinghpuri/topsis_by_ravsehaj
Author: Ravsehaj Singh Puri
Author-email: ravsehajsinghpuri@gmail.com
License: UNKNOWN
Platform: UNKNOWN
Classifier: Programming Language :: Python :: 3
Classifier: License :: OSI Approved :: MIT License
Classifier: Operating System :: OS Independent
Requires-Python: >=3.6
